<?xml version="1.0" encoding="UTF-8"?>
<objects serializationModel="Studio.02.02.00">
	<object class="AudioFile" id="{6dbc02a0-93d8-4fff-b07a-c46cd475223e}">
		<property name="assetPath">
			<value>Enemy_Hit_01.wav</value>
		</property>
		<property name="frequencyInKHz">
			<value>32</value>
		</property>
		<property name="channelCount">
			<value>1</value>
		</property>
		<property name="length">
			<value>0.34940624999999997</value>
		</property>
		<relationship name="masterAssetFolder">
			<destination>{1ca92f72-adff-40e7-9f2a-8a69708e595c}</destination>
		</relationship>
	</object>
</objects>
